slurpit_nautobot/__init__.py
slurpit_nautobot/api/__init__.py
slurpit_nautobot/api/serializers.py
slurpit_nautobot/api/urls.py
slurpit_nautobot/api/views.py
slurpit_nautobot/decorators.py
slurpit_nautobot/filtersets.py
slurpit_nautobot/forms.py
slurpit_nautobot/importer.py
slurpit_nautobot/management/__init__.py
slurpit_nautobot/management/choices.py
slurpit_nautobot/migrations/0001_initial.py
slurpit_nautobot/migrations/0002_auto_20240603_0415.py
slurpit_nautobot/migrations/0003_slurpitinterface.py
slurpit_nautobot/migrations/0004_slurpitinterface_enable_reconcile.py
slurpit_nautobot/migrations/0005_slurpitprefix.py
slurpit_nautobot/migrations/0006_auto_20240604_1011.py
slurpit_nautobot/migrations/0007_alter_slurpitprefix_prefix_length.py
slurpit_nautobot/migrations/0008_auto_20240808_0821.py
slurpit_nautobot/migrations/0009_auto_20240809_0701.py
slurpit_nautobot/migrations/0010_auto_20240809_0716.py
slurpit_nautobot/migrations/0011_slurpitipaddress_ignore_dns_name.py
slurpit_nautobot/migrations/0012_slurpitvlan.py
slurpit_nautobot/migrations/0013_auto_20240827_1557.py
slurpit_nautobot/migrations/0014_remove_slurpitinterface__cable_peer_id_and_more.py
slurpit_nautobot/migrations/0015_delete_slurpitlog.py
slurpit_nautobot/migrations/0016_slurpitimporteddevice_location_and_more.py
slurpit_nautobot/migrations/0017_slurpitprefix_vrf.py
slurpit_nautobot/migrations/__init__.py
slurpit_nautobot/models/__init__.py
slurpit_nautobot/models/device.py
slurpit_nautobot/models/interface.py
slurpit_nautobot/models/ipam.py
slurpit_nautobot/models/mapping.py
slurpit_nautobot/models/planning.py
slurpit_nautobot/models/prefix.py
slurpit_nautobot/models/setting.py
slurpit_nautobot/models/vlan.py
slurpit_nautobot/navigation.py
slurpit_nautobot/references/__init__.py
slurpit_nautobot/references/generic.py
slurpit_nautobot/references/imports.py
slurpit_nautobot/search.py
slurpit_nautobot/slurpitch.py
slurpit_nautobot/tables.py
slurpit_nautobot/template_content.py
slurpit_nautobot-1.0.21.dist-info/METADATA
slurpit_nautobot-1.0.21.dist-info/WHEEL
slurpit_nautobot-1.0.21.dist-info/licenses/LICENSE
slurpit_nautobot-1.0.21.dist-info/RECORD
