Metadata-Version: 2.4
Name: slurpit_nautobot
Version: 1.0.21
Summary: 
License-File: LICENSE
Author: Pieter
Author-email: pieter@slurpit.io
Requires-Python: >=3.10
Classifier: Programming Language :: Python :: 3
Classifier: Programming Language :: Python :: 3.10
Classifier: Programming Language :: Python :: 3.11
Classifier: Programming Language :: Python :: 3.12
Classifier: Programming Language :: Python :: 3.13
Classifier: Programming Language :: Python :: 3.14
Requires-Dist: djangorestframework-bulk (>=0.2.1)
Requires-Dist: requests (>=2.31.0)
